binarey/__init__.py
binarey/binarey.py
binarey/binary.py
binarey-2.0.0.dist-info/LICENSE
binarey-2.0.0.dist-info/METADATA
binarey-2.0.0.dist-info/WHEEL
binarey-2.0.0.dist-info/top_level.txt
binarey-2.0.0.dist-info/RECORD
