Metadata-Version: 2.1
Name: binarey
Version: 2.0.0
Summary: A module that allows you to convert files to binary.
Home-page: https://github.com/DaMuffinDev/binarey
Author: DaMuffin
License: MIT
Keywords: binary,binarey,bineray,binery,python,reader,parser,converter,binaryreader,binaryparser,compressor,decompressor,binarycompressor,binaryparser
Platform: UNKNOWN
Classifier: License :: OSI Approved :: MIT License
Classifier: Programming Language :: Python :: 3
Classifier: Programming Language :: Python :: 3.10
Requires-Python: >=3.8
License-File: LICENSE
Requires-Dist: functools
Requires-Dist: argparse
Requires-Dist: json
Requires-Dist: os
